{
  "version": "7",
  "dialect": "postgresql",
  "entries": [
    {
      "idx": 0,
      "version": "7",
      "when": 1754836900539,
      "tag": "0000_clever_phil_sheldon",
      "breakpoints": true
    },
    {
      "idx": 1,
      "version": "7",
      "when": 1755091035497,
      "tag": "0001_dry_shooting_star",
      "breakpoints": true
    },
    {
      "idx": 2,
      "version": "7",
      "when": 1755213967935,
      "tag": "0002_condemned_kate_bishop",
      "breakpoints": true
    },
    {
      "idx": 3,
      "version": "7",
      "when": 1755467634737,
      "tag": "0003_wandering_secret_warriors",
      "breakpoints": true
    }
  ]
}